README.md
setup.cfg
setup.py
nomad_cbec_limit_cli/__init__.py
nomad_cbec_limit_cli/api_client.py
nomad_cbec_limit_cli/configuration.py
nomad_cbec_limit_cli/exceptions.py
nomad_cbec_limit_cli/model_utils.py
nomad_cbec_limit_cli/rest.py
nomad_cbec_limit_cli.egg-info/PKG-INFO
nomad_cbec_limit_cli.egg-info/SOURCES.txt
nomad_cbec_limit_cli.egg-info/dependency_links.txt
nomad_cbec_limit_cli.egg-info/requires.txt
nomad_cbec_limit_cli.egg-info/top_level.txt
nomad_cbec_limit_cli/api/__init__.py
nomad_cbec_limit_cli/api/health_api.py
nomad_cbec_limit_cli/api/limit_api.py
nomad_cbec_limit_cli/apis/__init__.py
nomad_cbec_limit_cli/model/__init__.py
nomad_cbec_limit_cli/model/api_response.py
nomad_cbec_limit_cli/model/api_response_data.py
nomad_cbec_limit_cli/models/__init__.py
test/test_api_response.py
test/test_api_response_data.py
test/test_health_api.py
test/test_limit_api.py