Metadata-Version: 2.1
Name: nomad-cbec-limit-cli
Version: 1.1.1
Summary: Nomad CBEC
Home-page: UNKNOWN
Author: OpenAPI Generator community
Author-email: paul@samarkand.global
License: UNKNOWN
Keywords: OpenAPI,OpenAPI-Generator,Nomad CBEC
Platform: UNKNOWN
Requires-Python: >=3.6
